{
  "rewardPoints": 3, 
  "startMoney": 30, 
  "soundFile": "6", 
  "board": {
    "fieldsOnPath": [
      61, 
      49, 
      37, 
      25, 
      13, 
      1, 
      2, 
      3, 
      15, 
      27, 
      39, 
      51, 
      63, 
      64, 
      65, 
      66, 
      67, 
      68, 
      69, 
      70, 
      58, 
      46, 
      45, 
      44, 
      43, 
      42, 
      41, 
      40
    ], 
    "rows": 6, 
    "columns": 12, 
    "forbiddenFields": []
  }, 
  "waves": [
    {
      "interval": 3000, 
      "enemies": [
        13, 
        14, 
        15, 
        13, 
        14, 
        15
      ]
    }, 
    {
      "interval": 2000, 
      "enemies": [
        13, 
        13, 
        14, 
        14, 
        15, 
        15
      ]
    }, 
    {
      "interval": 1800, 
      "enemies": [
        13, 
        13, 
        13, 
        14, 
        14, 
        14, 
        15, 
        15, 
        15
      ]
    }, 
    {
      "interval": 1500, 
      "enemies": [
        13, 
        14, 
        14, 
        15, 
        15, 
        15, 
        13, 
        14, 
        14, 
        15
      ]
    }, 
    {
      "interval": 1200, 
      "enemies": [
        14, 
        14, 
        15, 
        15, 
        14, 
        14, 
        15, 
        15, 
        14, 
        14
      ]
    }, 
    {
      "interval": 1000, 
      "enemies": [
        15, 
        14, 
        13, 
        15, 
        14, 
        13, 
        16, 
        16
      ]
    }, 
    {
      "interval": 1000, 
      "enemies": [
        15, 
        15, 
        15, 
        15, 
        15, 
        16, 
        16, 
        16, 
        16, 
        16
      ]
    }, 
    {
      "interval": 1000, 
      "enemies": [
        15, 
        16, 
        16, 
        15, 
        16, 
        16, 
        15, 
        16, 
        16
      ]
    }, 
    {
      "interval": 800, 
      "enemies": [
        16, 
        16, 
        16, 
        15, 
        15, 
        16, 
        16, 
        16, 
        15, 
        15
      ]
    }, 
    {
      "interval": 500, 
      "enemies": [
        16, 
        16, 
        16, 
        16, 
        16, 
        16, 
        16, 
        16, 
        16, 
        16
      ]
    }
  ]
}
